MANIFEST.in
README.md
setup.cfg
setup.py
versioneer.py
libconfig/__init__.py
libconfig/_version.py
libconfig/config.py
libconfig/evaluator.py
libconfig.egg-info/PKG-INFO
libconfig.egg-info/SOURCES.txt
libconfig.egg-info/dependency_links.txt
libconfig.egg-info/requires.txt
libconfig.egg-info/top_level.txt