Metadata-Version: 1.1
Name: libconfig
Version: 0.9.1
Summary: Library Configuration Library
Home-page: https://github.com/jaumebonet/libconfig
Author: Jaume Bonet
Author-email: jaume.bonet@gmail.com
License: MIT
Project-URL: Documentation, http://jaumebonet.cat/libconfig
Project-URL: Source, https://github.com/jaumebonet/libconfig/
Project-URL: Tracker, https://github.com/jaumebonet/libconfig/issues
Keywords: development
Platform: UNIX
Classifier: Development Status :: 5 - Production/Stable
Classifier: Intended Audience :: Developers
Classifier: Topic :: Software Development :: Build Tools
Classifier: License :: OSI Approved :: MIT License
Classifier: Programming Language :: Python :: 2
Classifier: Programming Language :: Python :: 2.7
Classifier: Programming Language :: Python :: 3
Classifier: Programming Language :: Python :: 3.4
Classifier: Programming Language :: Python :: 3.5
Classifier: Programming Language :: Python :: 3.6
